terragen_rpc/.gitignore
terragen_rpc/__init__.py
terragen_rpc/high.py
terragen_rpc/impl.py
terragen_rpc/jsonrpc.py
terragen_rpc-0.9.2.dist-info/METADATA
terragen_rpc-0.9.2.dist-info/WHEEL
terragen_rpc-0.9.2.dist-info/entry_points.txt
terragen_rpc-0.9.2.dist-info/license_files/LICENSE
terragen_rpc-0.9.2.dist-info/RECORD
