Metadata-Version: 2.1
Name: terragen-rpc
Version: 0.9.2
Summary: A Python API for remote interaction with Terragen by Planetside Software.
Project-URL: Docs, https://planetside.co.uk/docs/terragen-rpc/
Project-URL: GitHub, https://github.com/planetside-software/terragen-rpc
Author-email: Planetside Software <support@planetside.co.uk>
Classifier: License :: OSI Approved :: MIT License
Classifier: Operating System :: OS Independent
Classifier: Programming Language :: Python :: 3
Requires-Python: >=3.6
